{
    "myServerJSON": [
        {
            "id": 0,
            "name": "272 S Rexford Dr, Beverly Hills, CA 90212",
            "image": "https://unviajealamedida.com/wp-content/uploads/2018/08/anna-sullivan-635346-unsplash-768x576.jpg",
            "ubication": "Beverly Hills",
            "area": "150m2",
            "wc": 2,
            "rooms": 3,
            "type": "house",
            "status": "for sale",
            "price": "320.000 usd",
            "parking": 2,
            "owner": "Saul Montes",
            "contact": 12345678,
            "description": "Lorem ipsum, dolor sit amet consectetur adipisicing elit. Id sunt quas doloremque delectus in amet fugit voluptatem! Velit, quaerat architecto odit aperiam, incidunt minima quisquam ab, ipsam maxime beatae non!"
        },
        {
            "id": 1,
            "name": "Big Modern House in the City",
            "image": "https://blog.properati.com.ec/wp-content/uploads/2019/09/chuttersnap-7BbyM7GbWyw-unsplash-1024x684.jpg",
            "ubication": "California",
            "area": "200m2",
            "wc": 3,
            "rooms": 5,
            "type": "property",
            "status": "for rent",
            "price": "450.000 usd",
            "parking": 4,
            "owner": "Armando Casas",
            "contact": 12345678,
            "description": "Lorem ipsum, dolor sit amet consectetur adipisicing elit. Id sunt quas doloremque delectus in amet fugit voluptatem! Velit, quaerat architecto odit aperiam, incidunt minima quisquam ab, ipsam maxime beatae non!"
        },
        {
            "id": 2,
            "name": "Local Business in the Center of the City",
            "image": "https://images.squarespace-cdn.com/content/v1/5c17cb5c12b13fec67eef4d5/1610228100379-HZXOGWXEAS4IOSGIKWEY/image-asset.jpeg?format=1500w",
            "ubication": "New york",
            "area": "80m2",
            "wc": 2,
            "rooms": 3,
            "type": "local shop",
            "status": "for rent",
            "price": "270.000 usd",
            "parking": 1,
            "owner": "Cindy Nero",
            "contact": 12345678,
            "description": "Lorem ipsum, dolor sit amet consectetur adipisicing elit. Id sunt quas doloremque delectus in amet fugit voluptatem! Velit, quaerat architecto odit aperiam, incidunt minima quisquam ab, ipsam maxime beatae non!"
        },
        {
            "id": 3,
            "name": "Beautiful Apartment in Los Angeles",
            "image": "https://ecolec.es/wp-content/uploads/2019/11/responsabilidad-ampliada-del-productor-rap-electrodomesticos-ecolec.jpg",
            "ubication": "Los Angeles",
            "area": "95m2",
            "wc": 2,
            "rooms": 3,
            "type": "apartament",
            "status": "for sale",
            "price": "230.000 usd",
            "parking": 0,
            "owner": "Witney Houston",
            "contact": 12345678,
            "description": "Lorem ipsum, dolor sit amet consectetur adipisicing elit. Id sunt quas doloremque delectus in amet fugit voluptatem! Velit, quaerat architecto odit aperiam, incidunt minima quisquam ab, ipsam maxime beatae non!"
        },
        {
            "id": 4,
            "name": "Rural Farm Comfy",
            "image": "https://www.duffyheating.ie/site/assets/files/1214/boiler-size-blog.1110x1110.jpg",
            "ubication": "Beverly Hills",
            "area": "60m2",
            "wc": 1,
            "rooms": 2,
            "type": "property",
            "status": "for rent",
            "price": "190.000 usd",
            "parking": 0,
            "owner": "Cindy Nero",
            "contact": 12345678,
            "description": "Lorem ipsum, dolor sit amet consectetur adipisicing elit. Id sunt quas doloremque delectus in amet fugit voluptatem! Velit, quaerat architecto odit aperiam, incidunt minima quisquam ab, ipsam maxime beatae non!"
        },
        {
            "id": 5,
            "name": "Modern House on the Suburbs",
            "image": "https://images.pexels.com/photos/1115804/pexels-photo-1115804.jpeg?auto=compress&cs=tinysrgb&w=1260&h=750&dpr=1",
            "ubication": "California",
            "area": "100m2",
            "wc": 2,
            "rooms": 4,
            "type": "house",
            "status": "for sale",
            "price": "310.000 usd",
            "parking": 3,
            "owner": "Saul Montes",
            "contact": 12345678,
            "description": "Lorem ipsum, dolor sit amet consectetur adipisicing elit. Id sunt quas doloremque delectus in amet fugit voluptatem! Velit, quaerat architecto odit aperiam, incidunt minima quisquam ab, ipsam maxime beatae non!"
        }
    ]
}